{
    "Identifier": "eos5jef",
    "Slug": "test-model-2",
    "Status": "In progress",
    "Title": "Model test 2",
    "Description": "Lorem ipsum Lorem ipsum Lorem ipsum Lorem ipsum Lorem ipsum Lorem ipsum Lorem ipsum Lorem ipsum Lorem ipsum Lorem ipsum Lorem ipsum Lorem ipsum Lorem ipsum Lorem ipsum",
    "Mode": "",
    "Task": [],
    "Input": [],
    "Input Shape": "",
    "Output": [],
    "Output Type": [],
    "Output Shape": "",
    "Interpretation": "",
    "Tag": [
        "ESKAPE"
    ],
    "Publication": "https://ersilia.io",
    "Source Code": "https://ersilia.io",
    "License": "MIT"
}